{
  "bot_states": [
    {
      "ID": 0,
      "direction": 0.30398017902419538,
      "state": {},
      "x_position": -44.333520381136012,
      "y_position": 121.84197946866801
    },
    {
      "ID": 1,
      "direction": 0.51196491970296831,
      "state": {},
      "x_position": 117.19349897681016,
      "y_position": -92.759341817024435
    },
    {
      "ID": 2,
      "direction": 1.343903882418056,
      "state": {},
      "x_position": 144.09339349868767,
      "y_position": 41.147557731355469
    },
    {
      "ID": 3,
      "direction": 3.4993821039980411,
      "state": {},
      "x_position": -136.70905015294468,
      "y_position": -61.453514249032544
    },
    {
      "ID": 4,
      "direction": 2.5256353635474342,
      "state": {},
      "x_position": 64.298438092971807,
      "y_position": -135.35854029740838
    },
    {
      "ID": 5,
      "direction": 0.83339588257016284,
      "state": {},
      "x_position": 5.5804932952361357,
      "y_position": 12.330445892179178
    },
    {
      "ID": 6,
      "direction": 2.7903432153204144,
      "state": {},
      "x_position": 25.914092649511598,
      "y_position": -147.64216817714325
    },
    {
      "ID": 7,
      "direction": 0.32288788272226565,
      "state": {},
      "x_position": 65.635722429646549,
      "y_position": 134.3516253046626
    },
    {
      "ID": 8,
      "direction": 5.2199831405224728,
      "state": {},
      "x_position": -119.24310594653736,
      "y_position": -90.833894424060333
    },
    {
      "ID": 9,
      "direction": 1.3722654379651611,
      "state": {},
      "x_position": 131.06766162059554,
      "y_position": 72.650057383156636
    },
    {
      "ID": 10,
      "direction": 1.3533577342670911,
      "state": {},
      "x_position": 149.74817714486807,
      "y_position": 5.6659589909005801
    },
    {
      "ID": 11,
      "direction": 5.2767062516166856,
      "state": {},
      "x_position": -92.974331006593218,
      "y_position": -115.51227547744512
    },
    {
      "ID": 12,
      "direction": 2.7714355116223448,
      "state": {},
      "x_position": -9.3375184562493523,
      "y_position": -149.59430948818246
    },
    {
      "ID": 13,
      "direction": 3.4993821039980411,
      "state": {},
      "x_position": 133.2194726599752,
      "y_position": -62.076959219249488
    },
    {
      "ID": 14,
      "direction": -1.1235514501801069,
      "state": {},
      "x_position": -80.861631681783123,
      "y_position": 126.18002917546363
    }
  ],
  "ticks": 4855
}